tms_django_api_version/__init__.py
tms_django_api_version/apps.py
tms_django_api_version/views.py
tms_django_api_version-1.0.0.dist-info/METADATA
tms_django_api_version-1.0.0.dist-info/WHEEL
tms_django_api_version-1.0.0.dist-info/top_level.txt
tms_django_api_version-1.0.0.dist-info/RECORD
