Metadata-Version: 2.1
Name: tms-django-api-version
Version: 1.0.0
Summary: Simple API endpoint for app versionning
Home-page: https://github.com/tms-software/django-api-version
Author: Franck COUTOULY
Author-email: franck.coutouly@tms-software.ch
Classifier: Programming Language :: Python :: 3
Classifier: License :: OSI Approved :: MIT License
Classifier: Operating System :: OS Independent
Requires-Python: >=3.6, <4
Requires-Dist: django
Requires-Dist: djangorestframework
